Lab2/problem 2/traffic_light.v
// Moore FSM Traffic Light Controller
module traffic_light(
    input clk, reset, tick,
    output reg [1:0] NS, EW  // 00=Red, 01=Green, 10=Yellow
);
    // State encoding
    localparam NS_G = 0, NS_Y = 1, EW_G = 2, EW_Y = 3;

    reg [1:0] state, next_state;
    reg [2:0] count; // count ticks for each state

    // State register and tick-based counting
    always @(posedge clk or posedge reset) begin
        if (reset) begin
            state <= NS_G;
            count <= 0;
        end else if (tick) begin
            if ((state == NS_G && count == 4) ||
                (state == NS_Y && count == 1) ||
                (state == EW_G && count == 4) ||
                (state == EW_Y && count == 1)) begin
                state <= next_state;
                count <= 0;
            end else begin
                count <= count + 1;
            end
        end
    end

    // Next state logic
    always @(*) begin
        case (state)
            NS_G: next_state = NS_Y;
            NS_Y: next_state = EW_G;
            EW_G: next_state = EW_Y;
            EW_Y: next_state = NS_G;
            default: next_state = NS_G;
        endcase
    end

    // Output logic (Moore)
    always @(*) begin
        case (state)
            NS_G: begin NS = 2'b01; EW = 2'b00; end // NS green, EW red
            NS_Y: begin NS = 2'b10; EW = 2'b00; end // NS yellow, EW red
            EW_G: begin NS = 2'b00; EW = 2'b01; end // NS red, EW green
            EW_Y: begin NS = 2'b00; EW = 2'b10; end // NS red, EW yellow
            default: begin NS = 2'b00; EW = 2'b00; end
        endcase
    end
endmodule

Lab2/problem 2/tick_generator.v
// Tick Generator: Produces a single-cycle pulse every COUNT_MAX clock cycles
module tick_generator #(parameter COUNT_MAX = 20)(
    input clk, reset,
    output reg tick
);
    reg [$clog2(COUNT_MAX)-1:0] count;

    always @(posedge clk or posedge reset) begin
        if (reset) begin
            count <= 0;
            tick <= 0;
        end else if (count == COUNT_MAX-1) begin
            count <= 0;
            tick <= 1; // pulse for 1 clock cycle
        end else begin
            count <= count + 1;
            tick <= 0;
        end
    end
endmodule

Lab2/problem 2/tb_traffic_light.v
`timescale 1ns/1ps
module tb_traffic_light;
    reg clk, reset;
    wire tick;
    wire [1:0] NS, EW;

    // Generate clock
    initial begin
        clk = 0;
        forever #5 clk = ~clk; // 10 ns period
    end

    // Instantiate tick generator (scaled down for sim)
    tick_generator #(.COUNT_MAX(20)) tg(
        .clk(clk),
        .reset(reset),
        .tick(tick)
    );

    // Instantiate traffic light FSM
    traffic_light tl(
        .clk(clk),
        .reset(reset),
        .tick(tick),
        .NS(NS),
        .EW(EW)
    );

    // Stimulus
    initial begin
        $dumpfile("dump.vcd");
        $dumpvars(0, tb_traffic_light);

        reset = 1;
        #12 reset = 0;

        // Run long enough for two full cycles
        #800 $finish;
    end
endmodule

Lab2/problem 2/dump.vcd
$date
	Tue Aug 19 12:02:52 2025
$end
$version
	Icarus Verilog
$end
$timescale
	1ps
$end
$scope module tb_traffic_light $end
$var wire 1 ! tick $end
$var wire 2 " NS [1:0] $end
$var wire 2 # EW [1:0] $end
$var reg 1 $ clk $end
$var reg 1 % reset $end
$scope module tg $end
$var wire 1 $ clk $end
$var wire 1 % reset $end
$var parameter 32 & COUNT_MAX $end
$var reg 5 ' count [4:0] $end
$var reg 1 ! tick $end
$upscope $end
$scope module tl $end
$var wire 1 $ clk $end
$var wire 1 % reset $end
$var wire 1 ! tick $end
$var parameter 32 ( EW_G $end
$var parameter 32 ) EW_Y $end
$var parameter 32 * NS_G $end
$var parameter 32 + NS_Y $end
$var reg 2 , EW [1:0] $end
$var reg 2 - NS [1:0] $end
$var reg 3 . count [2:0] $end
$var reg 2 / next_state [1:0] $end
$var reg 2 0 state [1:0] $end
$upscope $end
$upscope $end
$enddefinitions $end
$comment Show the parameter values. $end
$dumpall
b1 +
b0 *
b11 )
b10 (
b10100 &
$end
#0
$dumpvars
b0 0
b1 /
b0 .
b1 -
b0 ,
b0 '
1%
0$
b0 #
b1 "
0!
$end
#5000
1$
#10000
0$
#12000
0%
#15000
b1 '
1$
#20000
0$
#25000
b10 '
1$
#30000
0$
#35000
b11 '
1$
#40000
0$
#45000
b100 '
1$
#50000
0$
#55000
b101 '
1$
#60000
0$
#65000
b110 '
1$
#70000
0$
#75000
b111 '
1$
#80000
0$
#85000
b1000 '
1$
#90000
0$
#95000
b1001 '
1$
#100000
0$
#105000
b1010 '
1$
#110000
0$
#115000
b1011 '
1$
#120000
0$
#125000
b1100 '
1$
#130000
0$
#135000
b1101 '
1$
#140000
0$
#145000
b1110 '
1$
#150000
0$
#155000
b1111 '
1$
#160000
0$
#165000
b10000 '
1$
#170000
0$
#175000
b10001 '
1$
#180000
0$
#185000
b10010 '
1$
#190000
0$
#195000
b10011 '
1$
#200000
0$
#205000
1!
b0 '
1$
#210000
0$
#215000
0!
b1 '
b1 .
1$
#220000
0$
#225000
b10 '
1$
#230000
0$
#235000
b11 '
1$
#240000
0$
#245000
b100 '
1$
#250000
0$
#255000
b101 '
1$
#260000
0$
#265000
b110 '
1$
#270000
0$
#275000
b111 '
1$
#280000
0$
#285000
b1000 '
1$
#290000
0$
#295000
b1001 '
1$
#300000
0$
#305000
b1010 '
1$
#310000
0$
#315000
b1011 '
1$
#320000
0$
#325000
b1100 '
1$
#330000
0$
#335000
b1101 '
1$
#340000
0$
#345000
b1110 '
1$
#350000
0$
#355000
b1111 '
1$
#360000
0$
#365000
b10000 '
1$
#370000
0$
#375000
b10001 '
1$
#380000
0$
#385000
b10010 '
1$
#390000
0$
#395000
b10011 '
1$
#400000
0$
#405000
1!
b0 '
1$
#410000
0$
#415000
0!
b1 '
b10 .
1$
#420000
0$
#425000
b10 '
1$
#430000
0$
#435000
b11 '
1$
#440000
0$
#445000
b100 '
1$
#450000
0$
#455000
b101 '
1$
#460000
0$
#465000
b110 '
1$
#470000
0$
#475000
b111 '
1$
#480000
0$
#485000
b1000 '
1$
#490000
0$
#495000
b1001 '
1$
#500000
0$
#505000
b1010 '
1$
#510000
0$
#515000
b1011 '
1$
#520000
0$
#525000
b1100 '
1$
#530000
0$
#535000
b1101 '
1$
#540000
0$
#545000
b1110 '
1$
#550000
0$
#555000
b1111 '
1$
#560000
0$
#565000
b10000 '
1$
#570000
0$
#575000
b10001 '
1$
#580000
0$
#585000
b10010 '
1$
#590000
0$
#595000
b10011 '
1$
#600000
0$
#605000
1!
b0 '
1$
#610000
0$
#615000
0!
b1 '
b11 .
1$
#620000
0$
#625000
b10 '
1$
#630000
0$
#635000
b11 '
1$
#640000
0$
#645000
b100 '
1$
#650000
0$
#655000
b101 '
1$
#660000
0$
#665000
b110 '
1$
#670000
0$
#675000
b111 '
1$
#680000
0$
#685000
b1000 '
1$
#690000
0$
#695000
b1001 '
1$
#700000
0$
#705000
b1010 '
1$
#710000
0$
#715000
b1011 '
1$
#720000
0$
#725000
b1100 '
1$
#730000
0$
#735000
b1101 '
1$
#740000
0$
#745000
b1110 '
1$
#750000
0$
#755000
b1111 '
1$
#760000
0$
#765000
b10000 '
1$
#770000
0$
#775000
b10001 '
1$
#780000
0$
#785000
b10010 '
1$
#790000
0$
#795000
b10011 '
1$
#800000
0$
#805000
1!
b0 '
1$
