Lab2/problem 1/seq_detect_mealy.v
module seq_detect_mealy(
    input clk, reset, x,
    output wire y
);
    reg [2:0] state;        // must be reg (storage element)
    wire [2:0] next_state;  // combinational output

    parameter S0=0, S1=1, S2=2, S3=3;

    // State register
    always @(posedge clk or posedge reset) begin
        if (reset)
            state <= S0;
        else
            state <= next_state;
    end

    // Next-state logic
    assign next_state = (state == S0 && x)  ? S1 :
                        (state == S0 && ~x) ? S0 :
                        (state == S1 && x)  ? S2 :
                        (state == S1 && ~x) ? S0 :
                        (state == S2 && ~x) ? S3 :
                        (state == S2 && x)  ? S2 :
                        (state == S3 && x)  ? S1 :
                                              S0;

    // Output logic (Mealy → depends on state & input)
    assign y = (state == S3 && x) ? 1 : 0;

endmodule

Lab2/problem 1/tb_seq_detect_mealy.v
`timescale 1ns/1ps
module tb_seq_detect_mealy;
    reg clk, reset, x;
    wire y;

    seq_detect_mealy dut(.clk(clk), .reset(reset), .x(x), .y(y));

    always #5 clk = ~clk;   // clock generation

    initial begin
        clk = 0; reset = 1; x = 0;
        #12 reset = 0;

        // Test input sequence: 11011011101
        @(posedge clk) x = 1;
        @(posedge clk) x = 1;
        @(posedge clk) x = 0;
        @(posedge clk) x = 1;
        @(posedge clk) x = 1;
        @(posedge clk) x = 0;
        @(posedge clk) x = 1;
        @(posedge clk) x = 1;
        @(posedge clk) x = 0;
        @(posedge clk) x = 1;

        #30 $finish;
    end

    initial begin
        $dumpfile("dump.vcd");
        $dumpvars(0, tb_seq_detect_mealy);
        $monitor("Time=%0t | x=%b | y=%b", $time, x, y);
    end
endmodule

Lab 2/dump.vcd
$date
	Mon Aug 18 17:25:44 2025
$end
$version
	Icarus Verilog
$end
$timescale
	1ps
$end
$scope module tb_seq_detect_mealy $end
$var wire 1 ! y $end
$var reg 1 " clk $end
$var reg 1 # reset $end
$var reg 1 $ x $end
$scope module dut $end
$var wire 1 " clk $end
$var wire 1 # reset $end
$var wire 1 $ x $end
$var wire 1 ! y $end
$var wire 3 % next_state [2:0] $end
$var parameter 32 & S0 $end
$var parameter 32 ' S1 $end
$var parameter 32 ( S2 $end
$var parameter 32 ) S3 $end
$var reg 3 * state [2:0] $end
$upscope $end
$upscope $end
$enddefinitions $end
$comment Show the parameter values. $end
$dumpall
b11 )
b10 (
b1 '
b0 &
$end
#0
$dumpvars
b0 *
b0 %
0$
1#
0"
0!
$end
#5000
1"
#10000
0"
#12000
0#
#15000
b1 %
1$
1"
#20000
0"
#25000
b10 %
b1 *
1"
#30000
0"
#35000
b10 *
b11 %
0$
1"
#40000
0"
#45000
1!
b11 *
b1 %
1$
1"
#50000
0"
#55000
b10 %
0!
b1 *
1"
#60000
0"
#65000
b10 *
b11 %
0$
1"
#70000
0"
#75000
1!
b11 *
b1 %
1$
1"
#80000
0"
#85000
b10 %
0!
b1 *
1"
#90000
0"
#95000
b10 *
b11 %
0$
1"
#100000
0"
#105000
1!
b11 *
b1 %
1$
1"
#110000
0"
#115000
b10 %
0!
b1 *
1"
#120000
0"
#125000
b10 %
b10 *
1"
